qlued/__init__.py
qlued/admin.py
qlued/api_v2.py
qlued/apps.py
qlued/fixtures/backend.json
qlued/migrations/0001_initial.py
qlued/migrations/__init__.py
qlued/models.py
qlued/schemas.py
qlued/storage_providers.py
qlued/urls.py
django_qlued-0.3.0.dist-info/LICENSE
django_qlued-0.3.0.dist-info/METADATA
django_qlued-0.3.0.dist-info/WHEEL
django_qlued-0.3.0.dist-info/entry_points.txt
django_qlued-0.3.0.dist-info/RECORD
