Metadata-Version: 2.1
Name: django-qlued
Version: 0.3.0
Summary: Django packages that enables validated cloud access to quantum hardware.
Home-page: https://github.com/Alqor-UG/django-qlued
License: Apache-2.0
Keywords: pydantic,quantum-hardware,django,django-ninja
Author: fretchen
Author-email: fred.jendrzejewski@gmail.com
Requires-Python: >=3.10,<4.0
Classifier: Development Status :: 4 - Beta
Classifier: Framework :: Django
Classifier: License :: OSI Approved :: Apache Software License
Classifier: Programming Language :: Python :: 3
Classifier: Programming Language :: Python :: 3.10
Classifier: Programming Language :: Python :: 3.11
Classifier: Programming Language :: Python :: 3.12
Requires-Dist: django-ninja (>=1.1.0,<2.0.0)
Requires-Dist: python-decouple (>=3.8,<4.0)
Requires-Dist: pytz (>=2024.1,<2025.0)
Requires-Dist: sqooler (>=0.9.0,<0.10.0)
Requires-Dist: whitenoise (>=6.6.0,<7.0.0)
Project-URL: Documentation, https://alqor-ug.github.io/django-qlued
Project-URL: Repository, https://github.com/Alqor-UG/django-qlued
